MANIFEST.in
README.md
setup.py
noat/__init__.py
noat.egg-info/PKG-INFO
noat.egg-info/SOURCES.txt
noat.egg-info/dependency_links.txt
noat.egg-info/not-zip-safe
noat.egg-info/top_level.txt