Metadata-Version: 1.0
Name: noat
Version: 1.0.1
Summary: Non-overlapping annotation HTML tag insertion.
Home-page: https://github.com/droptype/noat
Author: Alec Perkins
Author-email: alec@droptype.com
License: UNLICENSE
Keywords: html tags tagging annotations annotation text
Platform: UNKNOWN
Classifier: Development Status :: 5 - Production/Stable
Classifier: Intended Audience :: Developers
Classifier: License :: Public Domain
Classifier: Programming Language :: Python :: 3
Classifier: Programming Language :: Python :: 2
Classifier: Programming Language :: Python :: Implementation :: CPython
Classifier: Programming Language :: Python :: Implementation :: PyPy
Classifier: Topic :: Internet :: WWW/HTTP :: Dynamic Content
Classifier: Topic :: Text Processing :: Markup :: HTML
